Metadata-Version: 1.1
Name: wishbone-output-http
Version: 3.0.2
Summary: A Wishbone output module to submit data to a http API.
Home-page: https://github.com/wishbone-modules/wishbone-output-http
Author: Jelle Smet
Author-email: development@smetj.net
License: UNKNOWN
Download-URL: https://github.com/smetj/wishbone-output-http/tarball/master
Platform: Linux
Classifier: Development Status :: 5 - Production/Stable
Classifier: License :: OSI Approved :: GNU General Public License v3 or later (GPLv3+)
Classifier: Programming Language :: Python
Classifier: Programming Language :: Python :: 3
Classifier: Programming Language :: Python :: Implementation :: PyPy
Classifier: Intended Audience :: Developers
Classifier: Intended Audience :: System Administrators
